aida_interchange/__init__.py
aida_interchange/aifutils.py
aida_interchange/bounding_box.py
aida_interchange/ldc_time_component.py
aida_interchange/rdf_ontologies/__init__.py
aida_interchange/rdf_ontologies/aida_domain_ontologies_common.py
aida_interchange/rdf_ontologies/entity_relations.py
aida_interchange/rdf_ontologies/events_with_fringe.py
aida_interchange/rdf_ontologies/extended_entity.py
aida_interchange/rdf_ontologies/interchange_ontology.py
aida_interchange/rdf_ontologies/ldc_ontology.py
aida_interchange/rdf_ontologies/ldc_ontology_m36.py
aida_interchange-1.2.1.dist-info/METADATA
aida_interchange-1.2.1.dist-info/WHEEL
aida_interchange-1.2.1.dist-info/top_level.txt
aida_interchange-1.2.1.dist-info/RECORD
