Metadata-Version: 2.1
Name: aida-interchange
Version: 1.2.1
Summary: AIDA Interchange Format
Home-page: https://github.com/NextCenturyCorporation/AIDA-Interchange-Format
Author: Next Century Corporation
Author-email: aif-support@nextcentury.com
License: UNKNOWN
Platform: UNKNOWN
Classifier: Programming Language :: Python :: 3
Classifier: License :: OSI Approved :: MIT License
Classifier: Operating System :: OS Independent
Requires-Python: ~=3.0
Requires-Dist: rdflib
Requires-Dist: sphinx (>=2.0.1)
Requires-Dist: attrs (>=17.4.0)
Requires-Dist: typing-extensions
